pyigv/__init__.py
pyigv/alignment.py
pyigv-0.1.4.dist-info/licenses/LICENSE
pyigv-0.1.4.dist-info/METADATA
pyigv-0.1.4.dist-info/WHEEL
pyigv-0.1.4.dist-info/top_level.txt
pyigv-0.1.4.dist-info/RECORD
