Metadata-Version: 2.4
Name: PyIGV
Version: 0.1.4
Summary: A Python interface to IGV-style alignment visualization
Home-page: https://github.com/regev-lab/PyIGV
Author: Frank Liu
Author-email: frankliu@nyu.edu
License: MIT
Project-URL: Documentation, https://github.com/regev-lab/PyIGV#readme
Project-URL: Bug Tracker, https://github.com/regev-lab/PyIGV/issues
Project-URL: Source Code, https://github.com/regev-lab/PyIGV
Keywords: igv,alignment,visualization,bioinformatics,genomics
Classifier: Development Status :: 4 - Beta
Classifier: Intended Audience :: Developers
Classifier: Topic :: Scientific/Engineering :: Bio-Informatics
Classifier: Programming Language :: Python :: 3
Classifier: Programming Language :: Python :: 3.7
Classifier: Programming Language :: Python :: 3.8
Classifier: Programming Language :: Python :: 3.9
Classifier: Programming Language :: Python :: 3.10
Classifier: License :: OSI Approved :: MIT License
Classifier: Operating System :: OS Independent
Requires-Python: >=3.7
License-File: LICENSE
Requires-Dist: numpy>=1.19.0
Requires-Dist: matplotlib>=3.3.0
Requires-Dist: biopython>=1.86
Provides-Extra: dev
Requires-Dist: pytest>=6.0; extra == "dev"
Requires-Dist: flake8; extra == "dev"
Requires-Dist: black; extra == "dev"
Dynamic: license-file
